cookiepress/__init__.py
cookiepress/cli.py
cookiepress/cookiepress.py
cookiepress-0.1.5.dist-info/AUTHORS.rst
cookiepress-0.1.5.dist-info/LICENSE
cookiepress-0.1.5.dist-info/METADATA
cookiepress-0.1.5.dist-info/WHEEL
cookiepress-0.1.5.dist-info/entry_points.txt
cookiepress-0.1.5.dist-info/top_level.txt
cookiepress-0.1.5.dist-info/RECORD
