Metadata-Version: 2.1
Name: cookiepress
Version: 0.1.5
Summary: A project scaffold generator that moves beyond mere templates.
Home-page: https://github.com/elgertam/cookiepress
Author: Andrew M. Elgert
Author-email: andrew.elgert@gmail.com
License: BSD license
Keywords: cookiepress
Platform: UNKNOWN
Classifier: Development Status :: 2 - Pre-Alpha
Classifier: Intended Audience :: Developers
Classifier: License :: OSI Approved :: BSD License
Classifier: Natural Language :: English
Classifier: Programming Language :: Python :: 2
Classifier: Programming Language :: Python :: 2.7
Classifier: Programming Language :: Python :: 3
Classifier: Programming Language :: Python :: 3.4
Classifier: Programming Language :: Python :: 3.5
Classifier: Programming Language :: Python :: 3.6
Requires-Dist: Click (>=6.0)
